timem_mcp/__init__.py
timem_mcp/__main__.py
timem_mcp/client.py
timem_mcp/config.py
timem_mcp/server.py
timem_mcp-0.1.3.dist-info/METADATA
timem_mcp-0.1.3.dist-info/WHEEL
timem_mcp-0.1.3.dist-info/entry_points.txt
timem_mcp-0.1.3.dist-info/licenses/LICENSE
timem_mcp-0.1.3.dist-info/RECORD
