Metadata-Version: 2.4
Name: timem-mcp
Version: 0.1.3
Summary: TiMEM MCP Server - Model Context Protocol server for TiMEM Engine
Project-URL: Homepage, https://github.com/timem-cloud/timem-mcp
Project-URL: Documentation, https://docs.timem.cloud
Project-URL: Repository, https://github.com/timem-cloud/timem-mcp
Author-email: TiMEM Team <contact@timem.cloud>
License: MIT
License-File: LICENSE
Keywords: ai,mcp,memory,model-context-protocol,timem
Classifier: Development Status :: 4 - Beta
Classifier: Intended Audience :: Developers
Classifier: License :: OSI Approved :: MIT License
Classifier: Programming Language :: Python :: 3
Classifier: Programming Language :: Python :: 3.8
Classifier: Programming Language :: Python :: 3.9
Classifier: Programming Language :: Python :: 3.10
Classifier: Programming Language :: Python :: 3.11
Classifier: Programming Language :: Python :: 3.12
Requires-Python: >=3.8
Requires-Dist: fastmcp>=0.1.0
Requires-Dist: httpx>=0.24.0
Provides-Extra: dev
Requires-Dist: pytest-asyncio>=0.21.0; extra == 'dev'
Requires-Dist: pytest>=7.0.0; extra == 'dev'
